kadabra/__init__.py
kadabra/auth.py
kadabra/capture.py
kadabra/cli.py
kadabra/cli_old.py
kadabra/client.py
kadabra/config.py
kadabra/createapp/layout.py
kadabra/createapp/standard.py
kadabra/credentials.py
kadabra/decouple/dependency.py
kadabra/decouple/injector.py
kadabra/decouple/resolver.py
kadabra/decouple/serializer.py
kadabra/freeze.py
kadabra/kernel/shell.py
kadabra/lint.py
kadabra/polling.py
kadabra/publish.py
kadabra/server/app_session.py
kadabra/server/script_runner.py
kadabra/server/server.py
kadabra/share.py
kadabra/status.py
kadabra_client-0.0.1.dist-info/entry_points.txt
kadabra_client-0.0.1.dist-info/LICENSE
kadabra_client-0.0.1.dist-info/WHEEL
kadabra_client-0.0.1.dist-info/METADATA
kadabra_client-0.0.1.dist-info/RECORD
