Metadata-Version: 2.1
Name: kadabra-client
Version: 0.0.1
Summary: Share your code, data and visuals, directly from Jupyter
Home-page: https://1000words-hq.com
License: Proprietary
Keywords: jupyter,share
Author: Edouard Godfrey
Author-email: edouard@1000words-hq.com
Requires-Python: >=3.7.1,<4.0
Classifier: License :: Other/Proprietary License
Classifier: Programming Language :: Python :: 3
Classifier: Programming Language :: Python :: 3.10
Classifier: Programming Language :: Python :: 3.8
Classifier: Programming Language :: Python :: 3.9
Requires-Dist: Pillow (>=9.1.1,<10.0.0)
Requires-Dist: astor (>=0.8.1,<0.9.0)
Requires-Dist: boto3 (>=1.21.34,<2.0.0)
Requires-Dist: click (>=7.1.2)
Requires-Dist: importlib-metadata (>=4.11.4,<5.0.0)
Requires-Dist: ipython (>=5.5.0)
Requires-Dist: nanoid (>=2.0.0,<3.0.0)
Requires-Dist: pyflakes (>=2.4.0,<3.0.0)
Requires-Dist: python-graphql-client (>=0.4.3,<0.5.0)
Requires-Dist: requests (>=2.23.0)
Requires-Dist: requests-aws4auth (>=1.1.2,<2.0.0)
Requires-Dist: streamlit (>=1.10.0,<2.0.0)
Requires-Dist: thousandwords.core (>=0.7.0,<0.8.0)
Requires-Dist: tomlkit (>=0.11.0,<0.12.0)
Project-URL: Documentation, https://docs.1000words-hq.com
